[
    {
        "url": "https://github.com/kedro-org/kedro.git",
        "file_path": "kedro/ipython/__init__.py",
        "commit": "5f018acb",
        "range": "[1, 19, 1, 34]",
        "source_info_study": "# pylint: disable=global-statement",
        "source_info_extracted": "global-statement",
        "mapped_oracle_idx": 33
    },
    {
        "url": "https://github.com/kedro-org/kedro.git",
        "file_path": "kedro/ipython/__init__.py",
        "commit": "f49234ce",
        "range": null,
        "source_info_study": "# pylint: disable=global-statement",
        "source_info_extracted": null,
        "mapped_oracle_idx": 33
    }
]